piview/CPU.py
piview/GPU.py
piview/Hardware.py
piview/Host.py
piview/Network.py
piview/Storage.py
piview/Utils.py
piview/__init__.py
piview/piview.py
piview-2.1.0.dist-info/AUTHORS.md
piview-2.1.0.dist-info/LICENSE
piview-2.1.0.dist-info/METADATA
piview-2.1.0.dist-info/WHEEL
piview-2.1.0.dist-info/top_level.txt
piview-2.1.0.dist-info/RECORD
