Metadata-Version: 2.1
Name: piview
Version: 2.1.0
Summary: Raspberry Pi System/Hardware Information
Home-page: https://github.com/AdyGCode/piview
Author: Adrian Gould
Author-email: adrian.gould@nmtafe.wa.edu.au
License: GNU General Public License v3
Keywords: piview
Platform: UNKNOWN
Classifier: Development Status :: 4 - Beta
Classifier: Intended Audience :: Developers
Classifier: License :: OSI Approved :: Open Software License 3.0 (OSL-3.0)
Classifier: Natural Language :: English
Classifier: Programming Language :: Python :: 3
Classifier: Programming Language :: Python :: 3.6
Classifier: Programming Language :: Python :: 3.7
Classifier: Programming Language :: Python :: 3.8
Requires-Python: >=3.6
License-File: LICENSE
License-File: AUTHORS.md
Requires-Dist: psutil
